kristpy/__init__.py
kristpy/timer.py
kristpy-0.0.5.dist-info/METADATA
kristpy-0.0.5.dist-info/WHEEL
kristpy-0.0.5.dist-info/licenses/LICENSE
kristpy-0.0.5.dist-info/RECORD
